{
  "id": "3546730",
  "name": "Zetrix App 数字证书",
  "font_family": "iconfont",
  "css_prefix_text": "icon-",
  "description": "",
  "glyphs": [
    {
      "icon_id": "31307185",
      "name": "下载",
      "font_class": "xiazai",
      "unicode": "e842",
      "unicode_decimal": 59458
    },
    {
      "icon_id": "30311468",
      "name": "用户",
      "font_class": "yonghu1",
      "unicode": "e82f",
      "unicode_decimal": 59439
    },
    {
      "icon_id": "30854755",
      "name": "批量",
      "font_class": "piliang",
      "unicode": "e83e",
      "unicode_decimal": 59454
    },
    {
      "icon_id": "30854756",
      "name": "默认",
      "font_class": "moren",
      "unicode": "e83f",
      "unicode_decimal": 59455
    },
    {
      "icon_id": "30854757",
      "name": "添加",
      "font_class": "tianjia",
      "unicode": "e840",
      "unicode_decimal": 59456
    },
    {
      "icon_id": "30854758",
      "name": "扫码",
      "font_class": "saoma",
      "unicode": "e841",
      "unicode_decimal": 59457
    }
  ]
}
